README.rst
setup.py
AppMetrics.egg-info/PKG-INFO
AppMetrics.egg-info/SOURCES.txt
AppMetrics.egg-info/dependency_links.txt
AppMetrics.egg-info/top_level.txt
appmetrics/__init__.py
appmetrics/exceptions.py
appmetrics/histogram.py
appmetrics/meter.py
appmetrics/metrics.py
appmetrics/py3comp.py
appmetrics/reporter.py
appmetrics/simple_metrics.py
appmetrics/statistics.py
appmetrics/wsgi.py
appmetrics/tests/__init__.py
appmetrics/tests/test_histogram.py
appmetrics/tests/test_meter.py
appmetrics/tests/test_metrics.py
appmetrics/tests/test_reporter.py
appmetrics/tests/test_simple_metrics.py
appmetrics/tests/test_statistics.py
appmetrics/tests/test_wsgi.py