Metadata-Version: 1.1
Name: AppMetrics
Version: 0.3
Summary: Application metrics collector
Home-page: https://github.com/avalente/appmetrics
Author: Antonio Valente
Author-email: y3sman@gmail.com
License: Apache 2.0
Keywords: metrics,folsom,histogram,metric,monitor
Platform: Platform Independent
Classifier: Development Status :: 3 - Alpha
Classifier: Intended Audience :: Developers
Classifier: Intended Audience :: System Administrators
Classifier: License :: OSI Approved :: Apache Software License
Classifier: Topic :: Software Development :: Quality Assurance
Classifier: Topic :: System :: Monitoring
Classifier: Programming Language :: Python :: 2.7
Classifier: Programming Language :: Python :: 3.3
